sphinxnotes/any/__init__.py
sphinxnotes/any/directives.py
sphinxnotes/any/domain.py
sphinxnotes/any/errors.py
sphinxnotes/any/indices.py
sphinxnotes/any/roles.py
sphinxnotes/any/schema.py
sphinxnotes/any/template.py
sphinxnotes_any-2.5.dist-info/LICENSE
sphinxnotes_any-2.5.dist-info/METADATA
sphinxnotes_any-2.5.dist-info/WHEEL
sphinxnotes_any-2.5.dist-info/top_level.txt
sphinxnotes_any-2.5.dist-info/RECORD
