Metadata-Version: 2.1
Name: sphinxnotes-any
Version: 2.5
Summary: Sphinx domain for documenting anything
Author: Shengyu Zhang
Maintainer: Shengyu Zhang
Project-URL: homepage, https://sphinx.silverrainz.me/any
Project-URL: documentation, https://sphinx.silverrainz.me/any
Project-URL: repository, https://github.com/sphinx-notes/any
Project-URL: changelog, https://sphinx.silverrainz.me/any/changelog.html
Project-URL: tracker, https://github.com/sphinx-notes/any/issues
Keywords: sphinx,extension,documentation
Classifier: Environment :: Plugins
Classifier: Framework :: Sphinx
Classifier: Framework :: Sphinx :: Domain
Classifier: Framework :: Sphinx :: Extension
Classifier: License :: OSI Approved :: BSD License
Classifier: Operating System :: OS Independent
Classifier: Programming Language :: Python
Classifier: Programming Language :: Python :: 3
Classifier: Topic :: Documentation
Classifier: Topic :: Documentation :: Sphinx
Requires-Python: >=3.8
License-File: LICENSE
Requires-Dist: Sphinx>=4
Requires-Dist: Jinja2
Requires-Dist: wand>=0.6.11
Provides-Extra: dev
Requires-Dist: build; extra == "dev"
Requires-Dist: twine; extra == "dev"
Requires-Dist: cruft; extra == "dev"
Provides-Extra: docs
Requires-Dist: furo; extra == "docs"
Requires-Dist: sphinxnotes-any; extra == "docs"
Requires-Dist: sphinx-design; extra == "docs"
Requires-Dist: sphinx-copybutton; extra == "docs"
Requires-Dist: sphinxcontrib-gtagjs; extra == "docs"
Requires-Dist: sphinxnotes-comboroles; extra == "docs"
Provides-Extra: test
Requires-Dist: pytest; extra == "test"
